setup.py
dsbox/__init__.py
dsbox/datapreprocessing/__init__.py
dsbox/datapreprocessing/profiler/__init__.py
dsbox/datapreprocessing/profiler/data_profile.py
dsbox/datapreprocessing/profiler/feature_compute_hih.py
dsbox/datapreprocessing/profiler/feature_compute_lfh.py
dsbox/datapreprocessing/profiler/helper_funcs.py
dsbox_datapreprocessing.egg-info/PKG-INFO
dsbox_datapreprocessing.egg-info/SOURCES.txt
dsbox_datapreprocessing.egg-info/dependency_links.txt
dsbox_datapreprocessing.egg-info/not-zip-safe
dsbox_datapreprocessing.egg-info/requires.txt
dsbox_datapreprocessing.egg-info/top_level.txt