Metadata-Version: 1.2
Name: dsbox-datapreprocessing
Version: 0.2.0
Summary: DSBox data preprocssing tools
Home-page: https://github.com/usc-isi-i2/dsbox-cleaning.git
Author: Ke-Thia Yao
Author-email: kyao@isi.edu
License: MIT
Platform: UNKNOWN
Requires-Python: >=3.5
